freqfit/__init__.py
freqfit/_version.py
freqfit/constraints.py
freqfit/dataset.py
freqfit/experiment.py
freqfit/fc.py
freqfit/guess.py
freqfit/limit.py
freqfit/model.py
freqfit/parameters.py
freqfit/plot.py
freqfit/statistics.py
freqfit/workspace.py
freqfit/guesses/initial_guess_0vbb.py
freqfit/models/__init__.py
freqfit/models/constants.py
freqfit/models/correlated_efficiency_0vbb.py
freqfit/models/correlated_efficiency_0vbb_correlate_delta.py
freqfit/models/correlated_efficiency_0vbb_exponential_background.py
freqfit/models/correlated_efficiency_0vbb_exponential_with_offset_background.py
freqfit/models/correlated_efficiency_0vbb_linear_background.py
freqfit/models/gaussian_on_uniform.py
freqfit/models/linear_bkg.py
freqfit/models/mjd_0vbb.py
freqfit/models/onebin_poisson.py
freqfit-0.4.dist-info/METADATA
freqfit-0.4.dist-info/WHEEL
freqfit-0.4.dist-info/top_level.txt
freqfit-0.4.dist-info/RECORD
