Metadata-Version: 2.4
Name: freqfit
Version: 0.4
Summary: Python package for constructing frequentist limits from unbinned data
Author: 
Maintainer: 
Project-URL: Homepage, https://github.com/cenpa/freqfit
Project-URL: Bug Tracker, https://github.com/cenpa/freqfit/issues
Project-URL: Discussions, https://github.com/cenpa/freqfit/discussions
Project-URL: Changelog, https://github.com/cenpa/freqfit/releases
Classifier: Development Status :: 4 - Beta
Classifier: Intended Audience :: Developers
Classifier: Intended Audience :: Science/Research
Classifier: License :: OSI Approved :: GNU General Public License v3 (GPLv3)
Classifier: Operating System :: MacOS
Classifier: Operating System :: POSIX
Classifier: Operating System :: Unix
Classifier: Programming Language :: Python
Classifier: Programming Language :: Python :: 3
Classifier: Programming Language :: Python :: 3 :: Only
Classifier: Topic :: Scientific/Engineering
Requires-Python: >=3.8
Requires-Dist: h5py>=3.2
Requires-Dist: colorlog
Requires-Dist: iminuit>=2.31
Requires-Dist: matplotlib
Requires-Dist: numba>=0.58.1
Requires-Dist: numpy>=1.21
Requires-Dist: tabulate>=0.9.0
Requires-Dist: pyyaml>=6.0.2
Requires-Dist: scipy>=1.16.0
Requires-Dist: jinja2>=3.1.5
Provides-Extra: all
Requires-Dist: freqfit[test]; extra == "all"
Provides-Extra: test
Requires-Dist: pre-commit; extra == "test"
Requires-Dist: pytest>=6.0; extra == "test"
Requires-Dist: pytest-cov; extra == "test"
